wx_mp_svr/__init__.py
wx_mp_svr/app.py
wx_mp_svr/req_msg.py
wx_mp_svr/rsp_msg.py
wx_mp_svr/utils.py
wx_mp_svr-0.1.1.dist-info/METADATA
wx_mp_svr-0.1.1.dist-info/WHEEL
wx_mp_svr-0.1.1.dist-info/RECORD
