Metadata-Version: 2.1
Name: wx-mp-svr
Version: 0.1.1
Summary: Wechat Official Accounts Callback Server Framework
Project-URL: Homepage, https://github.com/easy-wx/wx-mp-svr
Project-URL: Issues, https://github.com/easy-wx/wx-mp-svr/issues
Author-email: panzhongxian <panzhongxian0532@gmail.com>
Classifier: License :: OSI Approved :: MIT License
Classifier: Operating System :: OS Independent
Classifier: Programming Language :: Python :: 3
Requires-Python: >=3.8
Requires-Dist: flask>=3.0.0
Requires-Dist: wx-crypt>=0.0.2
